ascii_geometry/__init__.py
ascii_geometry/context.py
ascii_geometry-0.1.0.dist-info/METADATA
ascii_geometry-0.1.0.dist-info/WHEEL
ascii_geometry-0.1.0.dist-info/top_level.txt
ascii_geometry-0.1.0.dist-info/RECORD
