Metadata-Version: 2.1
Name: ascii-geometry
Version: 0.1.0
Summary: Ascii library
Home-page: https://ascii-geometry.readthedocs.io/
Author: Hoxu
Author-email: danu.hoxuan@gmail.com
License: MIT
Classifier: Intended Audience :: Developers
Classifier: License :: OSI Approved :: MIT License
Classifier: Programming Language :: Python
Classifier: Programming Language :: Python :: 3
Classifier: Programming Language :: Python :: 3.6
Classifier: Programming Language :: Python :: 3.7
Classifier: Programming Language :: Python :: 3.8
Classifier: Programming Language :: Python :: 3.9
Classifier: Operating System :: OS Independent
